[
  {
    "active": "47894",
    "confirmed": "75278",
    "deaths": "2442",
    "deltaconfirmed": "948",
    "deltadeaths": "27",
    "deltarecovered": "484",
    "lastupdatedtime": "13/05/2020 19:22:23",
    "recovered": "24937",
    "state": "Total",
    "statecode": "TT",
    "statenotes": ""
  },
  {
    "active": "18381",
    "confirmed": "24427",
    "deaths": "921",
    "deltaconfirmed": "0",
    "deltadeaths": "0",
    "deltarecovered": "0",
    "lastupdatedtime": "12/05/2020 22:13:24",
    "recovered": "5125",
    "state": "Maharashtra",
    "statecode": "MH",
    "statenotes": "[10-May]<br>\n- Total numbers are updated to the final figure reported for 10th May. <br>\n- 665 cases added by MH govt. on 10th May due to data cleaning <br>\n- 143 cases added by MH govt. on 5th May due to data cleaning <br>\n- 796 cases added by MH govt. on 4th May due to data cleaning <br>"
  },
  {
    "active": "5121",
    "confirmed": "8904",
    "deaths": "537",
    "deltaconfirmed": "0",
    "deltadeaths": "0",
    "deltarecovered": "0",
    "lastupdatedtime": "12/05/2020 20:16:23",
    "recovered": "3246",
    "state": "Gujarat",
    "statecode": "GJ",
    "statenotes": ""
  },
  {
    "active": "6523",
    "confirmed": "8718",
    "deaths": "61",
    "deltaconfirmed": "0",
    "deltadeaths": "0",
    "deltarecovered": "0",
    "lastupdatedtime": "12/05/2020 22:48:24",
    "recovered": "2134",
    "state": "Tamil Nadu",
    "statecode": "TN",
    "statenotes": ""
  },
  {
    "active": "5034",
    "confirmed": "7998",
    "deaths": "106",
    "deltaconfirmed": "359",
    "deltadeaths": "20",
    "deltarecovered": "346",
    "lastupdatedtime": "13/05/2020 11:13:23",
    "recovered": "2858",
    "state": "Delhi",
    "statecode": "DL",
    "statenotes": "[10-May]<br>\n\nDelhi will be releasing bulletins in the morning, containing data of the previous day. We will add that data to the date on which the report is released, rather than the previous day."
  },
  {
    "active": "1699",
    "confirmed": "4278",
    "deaths": "120",
    "deltaconfirmed": "152",
    "deltadeaths": "3",
    "deltarecovered": "5",
    "lastupdatedtime": "13/05/2020 16:23:24",
    "recovered": "2459",
    "state": "Rajasthan",
    "statecode": "RJ",
    "statenotes": ""
  },
  {
    "active": "2088",
    "confirmed": "4173",
    "deaths": "225",
    "deltaconfirmed": "187",
    "deltadeaths": "0",
    "deltarecovered": "0",
    "lastupdatedtime": "13/05/2020 19:22:27",
    "recovered": "1860",
    "state": "Madhya Pradesh",
    "statecode": "MP",
    "statenotes": ""
  },
  {
    "active": "1709",
    "confirmed": "3664",
    "deaths": "82",
    "deltaconfirmed": "0",
    "deltadeaths": "0",
    "deltarecovered": "0",
    "lastupdatedtime": "12/05/2020 23:23:24",
    "recovered": "1873",
    "state": "Uttar Pradesh",
    "statecode": "UP",
    "statenotes": ""
  },
  {
    "active": "1363",
    "confirmed": "2173",
    "deaths": "198",
    "deltaconfirmed": "0",
    "deltadeaths": "0",
    "deltarecovered": "0",
    "lastupdatedtime": "12/05/2020 19:53:24",
    "recovered": "612",
    "state": "West Bengal",
    "statecode": "WB",
    "statenotes": "- Cases updated as per WB bulletin as it now provides total number of cases.<br>\n- Deaths due to comorbidities added to total deceased<br>\n- Zones updated as per WB bulletin<br>"
  },
  {
    "active": "948",
    "confirmed": "2137",
    "deaths": "47",
    "deltaconfirmed": "48",
    "deltadeaths": "1",
    "deltarecovered": "86",
    "lastupdatedtime": "13/05/2020 11:54:24",
    "recovered": "1142",
    "state": "Andhra Pradesh",
    "statecode": "AP",
    "statenotes": ""
  },
  {
    "active": "1711",
    "confirmed": "1914",
    "deaths": "32",
    "deltaconfirmed": "0",
    "deltadeaths": "0",
    "deltarecovered": "0",
    "lastupdatedtime": "12/05/2020 19:23:24",
    "recovered": "171",
    "state": "Punjab",
    "statecode": "PB",
    "statenotes": ""
  },
  {
    "active": "472",
    "confirmed": "1326",
    "deaths": "32",
    "deltaconfirmed": "0",
    "deltadeaths": "0",
    "deltarecovered": "0",
    "lastupdatedtime": "12/05/2020 21:52:24",
    "recovered": "822",
    "state": "Telangana",
    "statecode": "TG",
    "statenotes": ""
  },
  {
    "active": "474",
    "confirmed": "959",
    "deaths": "33",
    "deltaconfirmed": "34",
    "deltadeaths": "2",
    "deltarecovered": "18",
    "lastupdatedtime": "13/05/2020 18:08:24",
    "recovered": "451",
    "state": "Karnataka",
    "statecode": "KA",
    "statenotes": "One active case in KA reduced as a confirmed patient died of non-CoViD19 related reasons"
  },
  {
    "active": "469",
    "confirmed": "934",
    "deaths": "10",
    "deltaconfirmed": "0",
    "deltadeaths": "0",
    "deltarecovered": "0",
    "lastupdatedtime": "12/05/2020 19:23:25",
    "recovered": "455",
    "state": "Jammu and Kashmir",
    "statecode": "JK",
    "statenotes": ""
  },
  {
    "active": "543",
    "confirmed": "932",
    "deaths": "7",
    "deltaconfirmed": "53",
    "deltadeaths": "1",
    "deltarecovered": "0",
    "lastupdatedtime": "13/05/2020 19:13:24",
    "recovered": "382",
    "state": "Bihar",
    "statecode": "BR",
    "statenotes": ""
  },
  {
    "active": "427",
    "confirmed": "780",
    "deaths": "11",
    "deltaconfirmed": "0",
    "deltadeaths": "0",
    "deltarecovered": "0",
    "lastupdatedtime": "12/05/2020 21:42:25",
    "recovered": "342",
    "state": "Haryana",
    "statecode": "HR",
    "statenotes": ""
  },
  {
    "active": "392",
    "confirmed": "538",
    "deaths": "3",
    "deltaconfirmed": "101",
    "deltadeaths": "0",
    "deltarecovered": "27",
    "lastupdatedtime": "13/05/2020 17:22:24",
    "recovered": "143",
    "state": "Odisha",
    "statecode": "OR",
    "statenotes": ""
  },
  {
    "active": "41",
    "confirmed": "535",
    "deaths": "4",
    "deltaconfirmed": "10",
    "deltadeaths": "0",
    "deltarecovered": "1",
    "lastupdatedtime": "13/05/2020 18:13:25",
    "recovered": "490",
    "state": "Kerala",
    "statecode": "KL",
    "statenotes": "Mahe native who expired in Kannur included in Kerala's tally"
  },
  {
    "active": "156",
    "confirmed": "189",
    "deaths": "3",
    "deltaconfirmed": "2",
    "deltadeaths": "0",
    "deltarecovered": "0",
    "lastupdatedtime": "13/05/2020 15:42:24",
    "recovered": "30",
    "state": "Chandigarh",
    "statecode": "CH",
    "statenotes": ""
  },
  {
    "active": "90",
    "confirmed": "172",
    "deaths": "3",
    "deltaconfirmed": "0",
    "deltadeaths": "0",
    "deltarecovered": "0",
    "lastupdatedtime": "12/05/2020 21:42:26",
    "recovered": "79",
    "state": "Jharkhand",
    "statecode": "JH",
    "statenotes": ""
  },
  {
    "active": "152",
    "confirmed": "154",
    "deaths": "0",
    "deltaconfirmed": "0",
    "deltadeaths": "0",
    "deltarecovered": "0",
    "lastupdatedtime": "12/05/2020 23:13:25",
    "recovered": "2",
    "state": "Tripura",
    "statecode": "TR",
    "statenotes": ""
  },
  {
    "active": "24",
    "confirmed": "71",
    "deaths": "1",
    "deltaconfirmed": "2",
    "deltadeaths": "0",
    "deltarecovered": "0",
    "lastupdatedtime": "13/05/2020 19:22:28",
    "recovered": "46",
    "state": "Uttarakhand",
    "statecode": "UT",
    "statenotes": ""
  },
  {
    "active": "25",
    "confirmed": "66",
    "deaths": "3",
    "deltaconfirmed": "0",
    "deltadeaths": "0",
    "deltarecovered": "0",
    "lastupdatedtime": "12/05/2020 22:52:24",
    "recovered": "35",
    "state": "Himachal Pradesh",
    "statecode": "HP",
    "statenotes": "HP has 4 Migrated cases which are reduced from Active #. Also, death of Tibetan refugee is included in deceased numbers, but not in confirmed"
  },
  {
    "active": "22",
    "confirmed": "65",
    "deaths": "2",
    "deltaconfirmed": "0",
    "deltadeaths": "0",
    "deltarecovered": "0",
    "lastupdatedtime": "13/05/2020 19:22:29",
    "recovered": "40",
    "state": "Assam",
    "statecode": "AS",
    "statenotes": "Includes one case from Nagaland <br>\nOne patient who migrated to Bihar has been reduced from Active count"
  },
  {
    "active": "6",
    "confirmed": "59",
    "deaths": "0",
    "deltaconfirmed": "0",
    "deltadeaths": "0",
    "deltarecovered": "0",
    "lastupdatedtime": "11/05/2020 12:33:25",
    "recovered": "53",
    "state": "Chhattisgarh",
    "statecode": "CT",
    "statenotes": ""
  },
  {
    "active": "20",
    "confirmed": "42",
    "deaths": "0",
    "deltaconfirmed": "0",
    "deltadeaths": "0",
    "deltarecovered": "0",
    "lastupdatedtime": "11/05/2020 22:14:25",
    "recovered": "22",
    "state": "Ladakh",
    "statecode": "LA",
    "statenotes": ""
  },
  {
    "active": "0",
    "confirmed": "33",
    "deaths": "0",
    "deltaconfirmed": "0",
    "deltadeaths": "0",
    "deltarecovered": "0",
    "lastupdatedtime": "07/05/2020 22:24:57",
    "recovered": "33",
    "state": "Andaman and Nicobar Islands",
    "statecode": "AN",
    "statenotes": ""
  },
  {
    "active": "1",
    "confirmed": "13",
    "deaths": "1",
    "deltaconfirmed": "0",
    "deltadeaths": "0",
    "deltarecovered": "1",
    "lastupdatedtime": "13/05/2020 11:13:25",
    "recovered": "11",
    "state": "Meghalaya",
    "statecode": "ML",
    "statenotes": ""
  },
  {
    "active": "3",
    "confirmed": "12",
    "deaths": "0",
    "deltaconfirmed": "0",
    "deltadeaths": "0",
    "deltarecovered": "0",
    "lastupdatedtime": "11/05/2020 11:42:24",
    "recovered": "9",
    "state": "Puducherry",
    "statecode": "PY",
    "statenotes": ""
  },
  {
    "active": "0",
    "confirmed": "7",
    "deaths": "0",
    "deltaconfirmed": "0",
    "deltadeaths": "0",
    "deltarecovered": "0",
    "lastupdatedtime": "19/04/2020 17:04:07",
    "recovered": "7",
    "state": "Goa",
    "statecode": "GA",
    "statenotes": ""
  },
  {
    "active": "0",
    "confirmed": "2",
    "deaths": "0",
    "deltaconfirmed": "0",
    "deltadeaths": "0",
    "deltarecovered": "0",
    "lastupdatedtime": "20/04/2020 10:04:08",
    "recovered": "2",
    "state": "Manipur",
    "statecode": "MN",
    "statenotes": ""
  },
  {
    "active": "0",
    "confirmed": "1",
    "deaths": "0",
    "deltaconfirmed": "0",
    "deltadeaths": "0",
    "deltarecovered": "0",
    "lastupdatedtime": "05/05/2020 22:32:47",
    "recovered": "1",
    "state": "Mizoram",
    "statecode": "MZ",
    "statenotes": ""
  },
  {
    "active": "0",
    "confirmed": "1",
    "deaths": "0",
    "deltaconfirmed": "0",
    "deltadeaths": "0",
    "deltarecovered": "0",
    "lastupdatedtime": "16/04/2020 19:33:11",
    "recovered": "1",
    "state": "Arunachal Pradesh",
    "statecode": "AR",
    "statenotes": ""
  },
  {
    "active": "0",
    "confirmed": "1",
    "deaths": "0",
    "deltaconfirmed": "0",
    "deltadeaths": "0",
    "deltarecovered": "0",
    "lastupdatedtime": "12/05/2020 23:23:25",
    "recovered": "1",
    "state": "Dadra and Nagar Haveli and Daman and Diu",
    "statecode": "DN",
    "statenotes": ""
  },
  {
    "active": "0",
    "confirmed": "0",
    "deaths": "0",
    "deltaconfirmed": "0",
    "deltadeaths": "0",
    "deltarecovered": "0",
    "lastupdatedtime": "20/04/2020 08:45:07",
    "recovered": "0",
    "state": "Nagaland",
    "statecode": "NL",
    "statenotes": ""
  },
  {
    "active": "0",
    "confirmed": "0",
    "deaths": "0",
    "deltaconfirmed": "0",
    "deltadeaths": "0",
    "deltarecovered": "0",
    "lastupdatedtime": "26/03/2020 07:19:29",
    "recovered": "0",
    "state": "Daman and Diu",
    "statecode": "DD",
    "statenotes": ""
  },
  {
    "active": "0",
    "confirmed": "0",
    "deaths": "0",
    "deltaconfirmed": "0",
    "deltadeaths": "0",
    "deltarecovered": "0",
    "lastupdatedtime": "26/03/2020 07:19:29",
    "recovered": "0",
    "state": "Lakshadweep",
    "statecode": "LD",
    "statenotes": ""
  },
  {
    "active": "0",
    "confirmed": "0",
    "deaths": "0",
    "deltaconfirmed": "0",
    "deltadeaths": "0",
    "deltarecovered": "0",
    "lastupdatedtime": "26/03/2020 07:19:29",
    "recovered": "0",
    "state": "Sikkim",
    "statecode": "SK",
    "statenotes": ""
  }
]
